swarmauri_toolkit_containertoolkit/ContainerToolkit.py
swarmauri_toolkit_containertoolkit/__init__.py
swarmauri_toolkit_containertoolkit-0.7.5.dist-info/LICENSE
swarmauri_toolkit_containertoolkit-0.7.5.dist-info/METADATA
swarmauri_toolkit_containertoolkit-0.7.5.dist-info/WHEEL
swarmauri_toolkit_containertoolkit-0.7.5.dist-info/entry_points.txt
swarmauri_toolkit_containertoolkit-0.7.5.dist-info/RECORD
