Metadata-Version: 2.3
Name: swarmauri_toolkit_containertoolkit
Version: 0.7.5
Summary: Toolkit bundling container management tools.
License: Apache-2.0
Author: Jacob Stewart
Author-email: jacob@swarmauri.com
Requires-Python: >=3.10,<3.13
Classifier: License :: OSI Approved :: Apache Software License
Classifier: Programming Language :: Python :: 3.10
Classifier: Programming Language :: Python :: 3.11
Classifier: Programming Language :: Python :: 3.12
Requires-Dist: swarmauri_base
Requires-Dist: swarmauri_core
Requires-Dist: swarmauri_standard
Requires-Dist: swarmauri_tool_containerfeedchars
Requires-Dist: swarmauri_tool_containermakepr
Requires-Dist: swarmauri_tool_containernewsession
